st_cli.py
simpletuner/__init__.py
simpletuner/__main__.py
simpletuner/cog.py
simpletuner/configure.py
simpletuner/lycoris_defaults.py
simpletuner/service_worker.py
simpletuner/train.py
simpletuner/worker_agent.py
simpletuner/cli/__init__.py
simpletuner/cli/__main__.py
simpletuner/cli/backup.py
simpletuner/cli/common.py
simpletuner/cli/configure.py
simpletuner/cli/database.py
simpletuner/cli/examples.py
simpletuner/cli/jobs.py
simpletuner/cli/metrics.py
simpletuner/cli/notifications.py
simpletuner/cli/quota.py
simpletuner/cli/server.py
simpletuner/cli/train.py
simpletuner/cli/webhooks.py
simpletuner/cli/worker.py
simpletuner/cli/auth/__init__.py
simpletuner/cli/auth/audit.py
simpletuner/cli/auth/orgs.py
simpletuner/cli/auth/users.py
simpletuner/cli/cloud/__init__.py
simpletuner/cli/cloud/api.py
simpletuner/cli/cloud/approval.py
simpletuner/cli/cloud/audit.py
simpletuner/cli/cloud/config.py
simpletuner/cli/cloud/cost_limit.py
simpletuner/cli/cloud/jobs.py
simpletuner/cli/cloud/notifications.py
simpletuner/cli/cloud/orgs.py
simpletuner/cli/cloud/quota.py
simpletuner/cli/cloud/users.py
simpletuner/custom-trackers/README.md
simpletuner/custom-trackers/test_tracker.py
simpletuner/diff2flow/__init__.py
simpletuner/diff2flow/bridge.py
simpletuner/examples/README.md
simpletuner/examples/acestep-audio.json
simpletuner/examples/default.json
simpletuner/examples/lycoris_config.json
simpletuner/examples/multidatabackend-controlnet-1024px.json
simpletuner/examples/multidatabackend-controlnet-128px.json
simpletuner/examples/multidatabackend-controlnet-512px.json
simpletuner/examples/multidatabackend-reference-512px.json
simpletuner/examples/multidatabackend-small-dreambooth-1024px.json
simpletuner/examples/multidatabackend-small-dreambooth-512px.json
simpletuner/examples/multidatabackend-small-video-480p+2s24fps.json
simpletuner/examples/multidatabackend-small-video-480p.json
simpletuner/examples/ace_step.peft-lora/config.json
simpletuner-4.0.1.dist-info/licenses/LICENSE
simpletuner-4.0.1.dist-info/METADATA
simpletuner-4.0.1.dist-info/WHEEL
simpletuner-4.0.1.dist-info/entry_points.txt
simpletuner-4.0.1.dist-info/top_level.txt
simpletuner-4.0.1.dist-info/RECORD
