Metadata-Version: 2.4
Name: simpletuner
Version: 4.0.1
Summary: Stable Diffusion 2.x and XL tuner.
Home-page: https://github.com/bghira/SimpleTuner
Author: bghira
Maintainer: bghira
License-Expression: AGPL-3.0-or-later
Project-URL: Homepage, https://github.com/bghira/SimpleTuner
Project-URL: Repository, https://github.com/bghira/SimpleTuner.git
Project-URL: Issues, https://github.com/bghira/SimpleTuner/issues
Project-URL: Documentation, https://simpletuner.dev
Project-URL: Changelog, https://github.com/bghira/SimpleTuner/releases
Keywords: stable-diffusion,machine-learning,deep-learning,pytorch,cuda,rocm,diffusion-models,ai,image-generation
Classifier: Development Status :: 4 - Beta
Classifier: Intended Audience :: Developers
Classifier: Intended Audience :: Science/Research
Classifier: Programming Language :: Python :: 3
Classifier: Programming Language :: Python :: 3.12
Classifier: Programming Language :: Python :: 3.13
Classifier: Topic :: Scientific/Engineering :: Artificial Intelligence
Classifier: Topic :: Multimedia :: Graphics
Classifier: Topic :: Software Development :: Libraries :: Python Modules
Classifier: Operating System :: OS Independent
Requires-Python: >=3.12,<3.14
License-File: LICENSE
Requires-Dist: diffusers>=0.36.0
Requires-Dist: transformers>=4.55.0
Requires-Dist: hf_transfer>=0.1.0
Requires-Dist: datasets>=3.0.1
Requires-Dist: wandb>=0.21.0
Requires-Dist: requests>=2.32.4
Requires-Dist: pillow>=11.3.0
Requires-Dist: trainingsample>=0.2.10
Requires-Dist: accelerate>=1.5.2
Requires-Dist: safetensors>=0.5.3
Requires-Dist: compel>=2.1.1
Requires-Dist: clip-interrogator>=0.6.0
Requires-Dist: open-clip-torch>=2.26.1
Requires-Dist: iterutils>=0.1.6
Requires-Dist: scipy>=1.11.1
Requires-Dist: boto3>=1.35.83
Requires-Dist: pandas>=2.2.3
Requires-Dist: botocore>=1.35.83
Requires-Dist: skrample>=0.5.0
Requires-Dist: urllib3<1.27
Requires-Dist: torchsde>=0.2.6
Requires-Dist: torchmetrics>=1.1.1
Requires-Dist: colorama>=0.4.6
Requires-Dist: numpy>=2.2.0
Requires-Dist: num2words>=0.5.13
Requires-Dist: peft>=0.17.0
Requires-Dist: tensorboard>=2.18.0
Requires-Dist: py3langid>=0.2.2
Requires-Dist: pypinyin>=0.50.0
Requires-Dist: sentencepiece>=0.2.0
Requires-Dist: spacy>=3.7.4
Requires-Dist: hangul-romanize>=0.1.0
Requires-Dist: optimum-quanto>=0.2.7
Requires-Dist: lycoris-lora>=3.4.0
Requires-Dist: torch-optimi>=0.2.1
Requires-Dist: librosa>=0.10.2
Requires-Dist: loguru>=0.7.2
Requires-Dist: toml>=0.10.2
Requires-Dist: fastapi[standard]>=0.115.0
Requires-Dist: sse-starlette>=1.6.5
Requires-Dist: atomicwrites>=1.4.1
Requires-Dist: beautifulsoup4>=4.12.3
Requires-Dist: prodigy-plus-schedule-free>=1.9.2
Requires-Dist: tokenizers>=0.21.0
Requires-Dist: huggingface-hub>=0.34.3
Requires-Dist: imageio-ffmpeg>=0.6.0
Requires-Dist: imageio[pyav]>=2.37.0
Requires-Dist: hf-xet>=1.1.5
Requires-Dist: peft-singlora>=0.2.0
Requires-Dist: cryptography>=41.0.0
Requires-Dist: torchcodec>=0.8.1
Requires-Dist: sdnq>=0.1.2
Requires-Dist: aiosqlite>=0.19.0
Requires-Dist: httpx>=0.28.0
Requires-Dist: torch>=2.9.1
Requires-Dist: torchvision>=0.24.0
Requires-Dist: torchaudio>=2.4.1
Requires-Dist: torchao>=0.14.1
Provides-Extra: cuda
Requires-Dist: torch>=2.9.1; extra == "cuda"
Requires-Dist: torchvision>=0.24.0; extra == "cuda"
Requires-Dist: torchaudio>=2.4.1; extra == "cuda"
Requires-Dist: triton>=3.3.0; extra == "cuda"
Requires-Dist: bitsandbytes>=0.45.0; extra == "cuda"
Requires-Dist: deepspeed>=0.17.2; extra == "cuda"
Requires-Dist: torchao>=0.12.0; extra == "cuda"
Requires-Dist: nvidia-cudnn-cu12; extra == "cuda"
Requires-Dist: nvidia-nccl-cu12; extra == "cuda"
Requires-Dist: lm-eval>=0.4.4; extra == "cuda"
Provides-Extra: rocm
Requires-Dist: torch>=2.9.0; extra == "rocm"
Requires-Dist: torchvision>=0.24.0; extra == "rocm"
Requires-Dist: torchaudio>=2.4.1; extra == "rocm"
Requires-Dist: torchao>=0.11.0; extra == "rocm"
Provides-Extra: apple
Requires-Dist: torch>=2.9.1; extra == "apple"
Requires-Dist: torchvision>=0.24.0; extra == "apple"
Requires-Dist: torchaudio>=2.4.1; extra == "apple"
Requires-Dist: torchao>=0.11.0; extra == "apple"
Provides-Extra: cpu
Requires-Dist: torch>=2.9.1; extra == "cpu"
Requires-Dist: torchvision>=0.24.0; extra == "cpu"
Requires-Dist: torchaudio>=2.4.1; extra == "cpu"
Requires-Dist: torchao>=0.11.0; extra == "cpu"
Provides-Extra: jxl
Requires-Dist: pillow-jxl-plugin>=1.3.1; extra == "jxl"
Provides-Extra: dev
Requires-Dist: selenium>=4.0.0; extra == "dev"
Requires-Dist: coverage>=7.0.0; extra == "dev"
Requires-Dist: black>=23.0.0; extra == "dev"
Requires-Dist: isort>=5.12.0; extra == "dev"
Requires-Dist: flake8>=6.0.0; extra == "dev"
Requires-Dist: mypy>=1.0.0; extra == "dev"
Requires-Dist: pre-commit>=3.0.0; extra == "dev"
Provides-Extra: test
Requires-Dist: selenium>=4.0.0; extra == "test"
Requires-Dist: coverage>=7.0.0; extra == "test"
Provides-Extra: docs
Requires-Dist: mkdocs>=1.6.0; extra == "docs"
Requires-Dist: mkdocs-material>=9.5.0; extra == "docs"
Requires-Dist: mkdocs-static-i18n>=1.2.0; extra == "docs"
Requires-Dist: pymdown-extensions>=10.0; extra == "docs"
Provides-Extra: all
Requires-Dist: pillow-jxl-plugin>=1.3.1; extra == "all"
Requires-Dist: selenium>=4.0.0; extra == "all"
Requires-Dist: coverage>=7.0.0; extra == "all"
Requires-Dist: black>=23.0.0; extra == "all"
Requires-Dist: isort>=5.12.0; extra == "all"
Requires-Dist: flake8>=6.0.0; extra == "all"
Dynamic: home-page
Dynamic: license-file
Dynamic: requires-dist
Dynamic: requires-python
